Metadata-Version: 2.1
Name: zdansfil-left-pad
Version: 1.0
Summary: Just testing
Home-page: https://gitlab.fit.cvut.cz/zdansfil/pypip_foo.git
Author: Filipos Santos
Author-email: mail@haha.cz
License: No license
Platform: UNKNOWN
License-File: LICENSE.txt
